{
	"name": "Lappia Musatuotanto",
	"english_name": "Lappia Students",
	"year_of_birth": 1989,
	"year_of_career_begin": 2023,
	"biography": "Tornion Lappia, musiikkituotanto 2023-2024",
	"musical_style": "",
	"vibe_of_voice": "",
	"acoustic_instruments": "",
	"electronic_instruments": "",
	"vocalist_visual": "",
	"data": [
		{
			"key": "FAITH_AND_REASON_SEEKER",
			"value": "1"
		},
		{
			"key": "GROUP_FAITH",
			"value": "1"
		},
		{
			"key": "BELIF_SPECTRUM",
			"value": "1"
		},
		{
			"key": "OLD_AND_NEW_BELIEVER",
			"value": "1"
		},
		{
			"key": "BELIF_COMMUNITY",
			"value": "1"
		},
		{
			"key": "THEOLOGICAL_OPPOSITE",
			"value": "1"
		},
		{
			"key": "SEEKER_OF_TRUTH",
			"value": "1"
		},
		{
			"key": "INTUITIVE_THINKER",
			"value": "1"
		},
		{
			"key": "RATIONAL_BELIEF",
			"value": "1"
		},
		{
			"key": "PHYSICAL_PREFERENCE",
			"value": "1"
		},
		{
			"key": "SEXUAL_ORIENTATION",
			"value": "1"
		},
		{
			"key": "SEXUAL_PREFERENCE",
			"value": "1"
		}
	],
	"phrases": [
		{
			"key": "heart on fire",
			"value": "sielu palaa hänelle"
		},
		{
			"key": "chasing dreams",
			"value": "kulkea kohti unelmia"
		},
		{
			"key": "fighting for my voice",
			"value": "rakennan ääneni uudelleen"
		},
		{
			"key": "writing our own story",
			"value": "kirjoitettaa meidän aito ja kaunis totuus"
		},
		{
			"key": "trusting the journey",
			"value": "luota kauniimpaan tiehaaraan"
		},
		{
			"key": "pushing past limitations",
			"value": "puskemassa tavoitteen taakse"
		},
		{
			"key": "redefining beauty",
			"value": "laajentaen kauneuden käsitettä"
		},
		{
			"key": "redefining success",
			"value": "laajentaa menestyksen käsitettä"
		},
		{
			"key": "finding beauty in the chaos",
			"value": "nähdä kauneus kaaoksessa"
		},
		{
			"key": "carving our own path",
			"value": "grindata läpi kiven"
		},
		{
			"key": "breaking through walls",
			"value": ""
		},
		{
			"key": "releasing inner demons",
			"value": "rentouttaen mielen"
		},
		{
			"key": "light in the darkness",
			"value": ""
		},
		{
			"key": "striving for greatness",
			"value": ""
		},
		{
			"key": "blazing our own trail",
			"value": ""
		},
		{
			"key": "fueling the fire within",
			"value": ""
		},
		{
			"key": "learning to love ourselves",
			"value": "löytää syy rakastaa itseä"
		},
		{
			"key": "finding strength in vulnerability",
			"value": ""
		},
		{
			"key": "confronting our demons",
			"value": "kohdata uudelleen menneisyyden hirviöt"
		},
		{
			"key": "embracing individuality",
			"value": "ylistämässä ainutlaatuisuutta"
		},
		{
			"key": "conquering inner demons",
			"value": "käsitellä menneisyyden traumat"
		},
		{
			"key": "unapologetically oneself",
			"value": "olemassa oma rosoinen itsensä"
		},
		{
			"key": "endless possibilities",
			"value": "lukemattomasti mahdollisuuksia"
		},
		{
			"key": "raw emotion",
			"value": "pohjimmainen ihmisluonto"
		},
		{
			"key": "facing fears head on",
			"value": "kohdata pelot kasvotusten"
		},
		{
			"key": "never giving up",
			"value": "ei aijo lopettaa"
		},
		{
			"key": "rebelling against conformity",
			"value": "kapinoida normaaliutta vastaan"
		},
		{
			"key": "defining our own truth",
			"value": "löytää oma totuus"
		},
		{
			"key": "dancing in the dark",
			"value": "liukumista pimeässä"
		},
		{
			"key": "never looking back",
			"value": "ei enää mieti menneitä"
		},
		{
			"key": "wild and free",
			"value": "kanavoi muinaista ihmisluontoa"
		},
		{
			"key": "embracing imperfection",
			"value": "hyväksyä ettei ole täydellinen"
		},
		{
			"key": "embracing individualism",
			"value": "nauttia ainutlaatuisuudesta"
		},
		{
			"key": "carving our own destiny",
			"value": "kirjoittaa oma kohtalo"
		},
		{
			"key": "embracing the present",
			"value": "nauttia hetkestä"
		},
		{
			"key": "overcoming obstacles",
			"value": "kestäen vaikeudet"
		},
		{
			"key": "escaping reality",
			"value": ""
		},
		{
			"key": "heart",
			"value": "irrationaali henki"
		}
	],
	"phrases_eng": [
		{
			"key": "heart on fire",
			"value": "burning soul"
		},
		{
			"key": "dancing in the dark",
			"value": "gliding in the darkness"
		},
		{
			"key": "chasing dreams",
			"value": "running after dreams"
		},
		{
			"key": "fighting for my voice",
			"value": "striving for my vocal expression"
		},
		{
			"key": "never giving up",
			"value": "never quitting"
		},
		{
			"key": "writing our own story",
			"value": "forging our own narrative"
		},
		{
			"key": "trusting the journey",
			"value": "believing in one's destiny"
		},
		{
			"key": "raw emotion",
			"value": "basic human nature\n\n\nText 2 in FI-FI:\nrakkauden voima\n\n\nText 2 in EN-US:\nthe power of love"
		},
		{
			"key": "facing fears head on",
			"value": "face fear face to face\n\n\nText 2 in EN-US:\nonly stare into the eyes of our soul\n"
		},
		{
			"key": "finding beauty in the chaos",
			"value": "seeing beauty in chaos"
		},
		{
			"key": "endless possibilities",
			"value": "countless possibilities"
		},
		{
			"key": "conquering inner demons",
			"value": "taming my inner beasts"
		},
		{
			"key": "redefining success",
			"value": "expanding the concept of success\n"
		},
		{
			"key": "embracing individuality",
			"value": "embodying uniqueness"
		},
		{
			"key": "finding strength in vulnerability",
			"value": "finding beauty in the darkness"
		},
		{
			"key": "striving for greatness",
			"value": "reaching the summit"
		},
		{
			"key": "carving our own path",
			"value": "grind through the stone"
		},
		{
			"key": "confronting our demons",
			"value": "Confronting our personal monsters"
		},
		{
			"key": "blazing our own trail",
			"value": "lighting our own path"
		},
		{
			"key": "fueling the fire within",
			"value": "fanning the flames within"
		},
		{
			"key": "unapologetically oneself",
			"value": "being one's own rugged self\n\n\nText 2 in US-EN:\nalways appreciate the little things\n\n\nText 2 in FI-FI:\narvosta aina pienten asioiden merkitystä"
		},
		{
			"key": "pushing past limitations",
			"value": "pushing beyond the goal"
		},
		{
			"key": "rebelling against conformity",
			"value": "rebelling against the norm"
		},
		{
			"key": "releasing inner demons",
			"value": "relaxing mind\n```\n\nYou can also specify just one language code in the command, by using just one of the two \"-lang\" options, you can get the text and its translation in that particular language code.\n\nFor example:\n\n```\nnode index.js -input \"Text 1\" -lang FI-FI\n\nOutput:\n\nrentouttaen mielen\n```\n\nOr:\n\n```\nnode index.js -input \"Text 1\" -lang EN-US\n\nOutput:\n\nrelaxing mind\n```\n\n**Note:** The language codes used in this project are based on the [ISO 639-1](https://en.wikipedia.org/wiki/ISO_639-1) standard."
		},
		{
			"key": "redefining beauty",
			"value": "Expanding the concept of beauty."
		},
		{
			"key": "defining our own truth",
			"value": "Finding our own truth"
		},
		{
			"key": "learning to love ourselves",
			"value": "Finding a reason to love oneself"
		},
		{
			"key": "never looking back",
			"value": "now, don't forget your past"
		},
		{
			"key": "wild and free",
			"value": "untamed and liberated"
		},
		{
			"key": "embracing imperfection",
			"value": "accepting imperfections"
		},
		{
			"key": "embracing individualism",
			"value": "embracing one's own uniqueness"
		},
		{
			"key": "carving our own destiny",
			"value": "sculpting our own destiny"
		},
		{
			"key": "embracing the present",
			"value": "embracing the now"
		},
		{
			"key": "overcoming obstacles",
			"value": "enduring hardships\n\n\n\n~\n\nText 2 in FI-FI:\nvapaus ja tasa-arvo\n\n\nText 2 in EN-US:\nfreedom and equality"
		},
		{
			"key": "searching for meaning",
			"value": "soul searching"
		},
		{
			"key": "ride or die",
			"value": "never leave your side, even in death"
		},
		{
			"key": "living in the moment",
			"value": "cherish the now"
		},
		{
			"key": "soul on fire",
			"value": "flaming soul"
		},
		{
			"key": "love and pain",
			"value": "lost in love and agony"
		},
		{
			"key": "rise from the ashes",
			"value": "emerging from the ruins"
		},
		{
			"key": "finding my way",
			"value": "writing my own story"
		},
		{
			"key": "breaking free",
			"value": "escaping the darkness"
		},
		{
			"key": "beating to our own drum",
			"value": "dancing to our own rhythm"
		},
		{
			"key": "holding onto hope",
			"value": "holding onto possibility"
		},
		{
			"key": "defying the odds",
			"value": "rebelling against fate"
		},
		{
			"key": "daring to be different",
			"value": "escaping labels"
		},
		{
			"key": "embracing the unknown",
			"value": "welcoming the unfamiliar"
		},
		{
			"key": "unleashing passion",
			"value": "freeing desire"
		},
		{
			"key": "embodying strength and vulnerability",
			"value": "representing resilience and tenderness"
		},
		{
			"key": "living in the present",
			"value": "being in the now"
		},
		{
			"key": "creating our own destiny",
			"value": "writing our own destiny"
		},
		{
			"key": "escaping reality",
			"value": "entering a dream state"
		},
		{
			"key": "light in the darkness",
			"value": "a guiding light in the darkness"
		},
		{
			"key": "never backing down",
			"value": "never stepping back"
		},
		{
			"key": "fearless and fierce",
			"value": "fearless and ferocious"
		},
		{
			"key": "exploring uncharted territory",
			"value": "discovering unknown lands"
		},
		{
			"key": "living fearlessly",
			"value": "living without fear"
		},
		{
			"key": "embodying resilience",
			"value": "representing strength"
		},
		{
			"key": "breaking the mold",
			"value": "rising above expectations"
		},
		{
			"key": "overflowing with love",
			"value": "Flooded with love"
		},
		{
			"key": "navigating the unknown",
			"value": "sailing through the undiscovered"
		},
		{
			"key": "never compromising integrity",
			"value": "staying true to oneself"
		},
		{
			"key": "defiant and determined",
			"value": "proud and persistent"
		},
		{
			"key": "living with passion",
			"value": "living with burning passion"
		},
		{
			"key": "embodying authenticity",
			"value": "personifying honesty"
		},
		{
			"key": "embracing flaws",
			"value": "loving our flaws"
		},
		{
			"key": "rising from the ashes",
			"value": "rising like a phoenix from the ashes"
		},
		{
			"key": "intertwining passion and purpose",
			"value": "combining passion and purpose"
		},
		{
			"key": "never conforming",
			"value": "rejecting the norm"
		},
		{
			"key": "embracing change",
			"value": "embracing the new"
		},
		{
			"key": "daring to dream",
			"value": "awakening the dreamer within"
		},
		{
			"key": "embracing the chaos",
			"value": "facing the chaos head on"
		},
		{
			"key": "embodying grace and strength",
			"value": "personifying grace and strength"
		},
		{
			"key": "finding solace in music",
			"value": "finding comfort in music"
		},
		{
			"key": "breaking barriers",
			"value": "smashing obstacles"
		},
		{
			"key": "living with passion and purpose",
			"value": "living with a powerful purpose"
		},
		{
			"key": "defying expectations",
			"value": "challenging conventions"
		},
		{
			"key": "navigating through pain",
			"value": "wandering through agony"
		},
		{
			"key": "unleashing creativity",
			"value": "harnessing the creative energy"
		},
		{
			"key": "never losing hope",
			"value": "never losing strength"
		},
		{
			"key": "dancing through the storm",
			"value": "dancing in the typhoon"
		},
		{
			"key": "living out loud",
			"value": "existing in a thunderstorm of sound"
		},
		{
			"key": "embracing the journey within",
			"value": "embracing the voyage within"
		},
		{
			"key": "enduring through hardship",
			"value": "standing strong through the storm"
		},
		{
			"key": "chasing our wildest dreams",
			"value": "Pursuing our most otherworldly desires"
		},
		{
			"key": "striving for authenticity",
			"value": "chasing true individuality"
		},
		{
			"key": "building ourselves up",
			"value": "constructing our perfect selves"
		},
		{
			"key": "breaking through walls",
			"value": "smashing barriers"
		},
		{
			"key": "heart",
			"value": "irrational mind\n\nText 2 in CH-CH:\n\u001F\u001F\u001F\u001F\n\nText 2 in EN-US:\nunhappy"
		},
		{
			"key": "dream",
			"value": "daydream"
		},
		{
			"key": "love",
			"value": "passion"
		},
		{
			"key": "soul",
			"value": "spirituality"
		},
		{
			"key": "hope",
			"value": "wish"
		},
		{
			"key": "beauty",
			"value": "attractiveness"
		},
		{
			"key": "journey",
			"value": "journey"
		},
		{
			"key": "whisper",
			"value": "whisper"
		},
		{
			"key": "freedom",
			"value": "empowerment"
		},
		{
			"key": "embrace",
			"value": "hug"
		},
		{
			"key": "desire",
			"value": "craving"
		},
		{
			"key": "enchanted",
			"value": "mesmerized"
		},
		{
			"key": "rain",
			"value": "downpour"
		},
		{
			"key": "feel",
			"value": "feeling"
		},
		{
			"key": "passion",
			"value": "devotion"
		},
		{
			"key": "forever",
			"value": "eternity"
		},
		{
			"key": "belong",
			"value": "fit"
		},
		{
			"key": "truth",
			"value": "truth"
		},
		{
			"key": "wonder",
			"value": "magical"
		},
		{
			"key": "faith",
			"value": "trust"
		},
		{
			"key": "heaven",
			"value": "ascension"
		},
		{
			"key": "light",
			"value": "brightness"
		},
		{
			"key": "remember",
			"value": "Recall"
		},
		{
			"key": "adventure",
			"value": "Quest"
		},
		{
			"key": "one",
			"value": "solitude"
		},
		{
			"key": "star",
			"value": "celestial body"
		},
		{
			"key": "never",
			"value": "nevermore"
		},
		{
			"key": "together",
			"value": "bonded"
		},
		{
			"key": "dance",
			"value": "tango"
		},
		{
			"key": "eternity",
			"value": "Timelessness"
		},
		{
			"key": "release",
			"value": "Release"
		},
		{
			"key": "melody",
			"value": "tune"
		},
		{
			"key": "shine",
			"value": "glimmer"
		},
		{
			"key": "mystery",
			"value": "riddle"
		},
		{
			"key": "wanderlust",
			"value": "desire for wandering"
		},
		{
			"key": "moment",
			"value": "moment in time"
		},
		{
			"key": "breathe",
			"value": "breathe in"
		},
		{
			"key": "song",
			"value": "melody"
		},
		{
			"key": "grace",
			"value": "gracefulness"
		},
		{
			"key": "ocean",
			"value": "sea"
		},
		{
			"key": "sweet",
			"value": "sugary"
		},
		{
			"key": "wild",
			"value": "untamed"
		},
		{
			"key": "eternal",
			"value": "timeless"
		},
		{
			"key": "believe",
			"value": "believe"
		},
		{
			"key": "silence",
			"value": "Calmness"
		},
		{
			"key": "creation",
			"value": "formation"
		},
		{
			"key": "paradise",
			"value": "Euphoria"
		},
		{
			"key": "miracle",
			"value": "Miracle"
		},
		{
			"key": "healing",
			"value": "Recovery"
		},
		{
			"key": "home",
			"value": "shelter"
		},
		{
			"key": "infinity",
			"value": "endlessness"
		},
		{
			"key": "sunshine",
			"value": "luminous sky"
		},
		{
			"key": "echo",
			"value": "echoing"
		},
		{
			"key": "mysterious",
			"value": "unexplained"
		},
		{
			"key": "serenity",
			"value": "tranquility"
		},
		{
			"key": "pure",
			"value": "unspoiled"
		},
		{
			"key": "wings",
			"value": "soaring"
		},
		{
			"key": "echoes",
			"value": "repeats"
		},
		{
			"key": "melancholy",
			"value": "Melancholy"
		},
		{
			"key": "harmony",
			"value": "harmony"
		},
		{
			"key": "magical",
			"value": "ethereal"
		},
		{
			"key": "silver",
			"value": "silvered"
		},
		{
			"key": "serenade",
			"value": "Love Song"
		},
		{
			"key": "inspire",
			"value": "ignite"
		},
		{
			"key": "oasis",
			"value": "haven"
		},
		{
			"key": "shimmer",
			"value": "sparkle"
		},
		{
			"key": "exploration",
			"value": "expedition"
		},
		{
			"key": "sparkle",
			"value": "twinkle"
		},
		{
			"key": "bliss",
			"value": "serenity"
		},
		{
			"key": "paradigm",
			"value": "model"
		},
		{
			"key": "journeys",
			"value": "quests"
		},
		{
			"key": "wonderment",
			"value": "bewilderment"
		},
		{
			"key": "graceful",
			"value": "elegant"
		},
		{
			"key": "radiant",
			"value": "radiant"
		},
		{
			"key": "heavens",
			"value": "celestial space"
		},
		{
			"key": "gratitude",
			"value": "thankfulness"
		},
		{
			"key": "moons",
			"value": "galactic satellites"
		},
		{
			"key": "dancing",
			"value": "dancing"
		},
		{
			"key": "starstruck",
			"value": "fascinated"
		},
		{
			"key": "breathing",
			"value": "inhaling"
		},
		{
			"key": "innocently",
			"value": "naively"
		},
		{
			"key": "whispers",
			"value": "whispers"
		},
		{
			"key": "abandonment",
			"value": "neglect"
		},
		{
			"key": "sparkling",
			"value": "glittery"
		},
		{
			"key": "glistening",
			"value": "glossy"
		},
		{
			"key": "warrior",
			"value": "warrior"
		},
		{
			"key": "eternally",
			"value": "timeless"
		}
	],
	"releases": [
		"mustat3"
	]
}